pybrainyquote.py
pybrainyquote-1.2.dist-info/entry_points.txt
pybrainyquote-1.2.dist-info/WHEEL
pybrainyquote-1.2.dist-info/METADATA
pybrainyquote-1.2.dist-info/RECORD
