Metadata-Version: 2.1
Name: pybrainyquote
Version: 1.2
Summary: Get quotes from brainyquote. Make you life positive.
Home-page: https://github.com/Freakwill/pybrainyquote
License: MIT
Keywords: brainyquote,crawler
Author: William Song
Author-email: 30965609+Freakwill@users.noreply.github.com
Requires-Python: >=3.7,<4.0
Classifier: Environment :: MacOS X
Classifier: Intended Audience :: Education
Classifier: License :: OSI Approved :: MIT License
Classifier: Operating System :: OS Independent
Classifier: Programming Language :: Python :: 3
Classifier: Programming Language :: Python :: 3.10
Classifier: Programming Language :: Python :: 3.7
Classifier: Programming Language :: Python :: 3.8
Classifier: Programming Language :: Python :: 3.9
Classifier: Topic :: Software Development :: Libraries :: Python Modules
Requires-Dist: bs4
Requires-Dist: furl
Requires-Dist: requests
Project-URL: Repository, https://github.com/Freakwill/pybrainyquote
